NeuronBit/__init__.py
NeuronBit/core.py
NeuronBit/tempCodeRunnerFile.py
neuronbit-0.2.1.dist-info/METADATA
neuronbit-0.2.1.dist-info/WHEEL
neuronbit-0.2.1.dist-info/top_level.txt
neuronbit-0.2.1.dist-info/RECORD
